chimera/__init__.py
chimera/api/__init__.py
chimera/api/configs.py
chimera/api/dto.py
chimera/api/exception.py
chimera/api/response.py
chimera/api/run.py
chimera/containers/Dockerfile.worker
chimera/containers/__init__.py
chimera/containers/configs.py
chimera/containers/workers.py
chimera/nodes/__init__.py
chimera/nodes/masters/__init__.py
chimera/nodes/masters/aggregation.py
chimera/nodes/masters/base.py
chimera/nodes/masters/parameter_server.py
chimera/nodes/workers/__init__.py
chimera/nodes/workers/model.py
chimera/nodes/workers/sgd.py
chimera/utils/__init__.py
chimera/utils/logger.py
chimera/utils/parse.py
chimera_distributed_ml-0.1.12.dist-info/LICENSE
chimera_distributed_ml-0.1.12.dist-info/METADATA
chimera_distributed_ml-0.1.12.dist-info/WHEEL
chimera_distributed_ml-0.1.12.dist-info/RECORD
