Metadata-Version: 2.3
Name: chimera-distributed-ml
Version: 0.1.12
Summary: 
Author: Samir Nunes da Silva
Requires-Python: >=3.12.6,<4.0.0
Classifier: Programming Language :: Python :: 3
Classifier: Programming Language :: Python :: 3.13
Requires-Dist: fastapi (>=0.115.8,<0.116.0)
Requires-Dist: pandas (>=2.2.3,<3.0.0)
Requires-Dist: pydantic (>=2.10.6,<3.0.0)
Requires-Dist: pydantic-settings (>=2.7.1,<3.0.0)
Requires-Dist: requests (>=2.32.3,<3.0.0)
Requires-Dist: scikit-learn (>=1.6.1,<2.0.0)
Requires-Dist: ucimlrepo (>=0.0.7,<0.0.8)
Requires-Dist: uvicorn (>=0.34.0,<0.35.0)
